sparkforge/__init__.py
sparkforge/compat.py
sparkforge/constants.py
sparkforge/errors.py
sparkforge/execution.py
sparkforge/functions.py
sparkforge/logging.py
sparkforge/performance.py
sparkforge/reporting.py
sparkforge/table_operations.py
sparkforge/types.py
sparkforge/dependencies/__init__.py
sparkforge/dependencies/analyzer.py
sparkforge/dependencies/exceptions.py
sparkforge/dependencies/graph.py
sparkforge/models/__init__.py
sparkforge/models/base.py
sparkforge/models/dependencies.py
sparkforge/models/enums.py
sparkforge/models/exceptions.py
sparkforge/models/execution.py
sparkforge/models/factory.py
sparkforge/models/pipeline.py
sparkforge/models/steps.py
sparkforge/models/types.py
sparkforge/pipeline/__init__.py
sparkforge/pipeline/builder.py
sparkforge/pipeline/models.py
sparkforge/pipeline/monitor.py
sparkforge/pipeline/runner.py
sparkforge/validation/__init__.py
sparkforge/validation/data_validation.py
sparkforge/validation/pipeline_validation.py
sparkforge/validation/utils.py
sparkforge/writer/__init__.py
sparkforge/writer/analytics.py
sparkforge/writer/core.py
sparkforge/writer/exceptions.py
sparkforge/writer/models.py
sparkforge/writer/monitoring.py
sparkforge/writer/operations.py
sparkforge/writer/query_builder.py
sparkforge/writer/storage.py
sparkforge-1.3.3.dist-info/LICENSE
sparkforge-1.3.3.dist-info/METADATA
sparkforge-1.3.3.dist-info/WHEEL
sparkforge-1.3.3.dist-info/top_level.txt
sparkforge-1.3.3.dist-info/RECORD
