Metadata-Version: 2.1
Name: sparkforge
Version: 1.3.3
Summary: A simplified, production-ready data pipeline builder for Apache Spark and Delta Lake
Author-email: Odos Matthews <odosmatthews@gmail.com>
Maintainer-email: Odos Matthews <odosmatthews@gmail.com>
License: MIT
Project-URL: Homepage, https://github.com/eddiethedean/sparkforge
Project-URL: Documentation, https://sparkforge.readthedocs.io/
Project-URL: Repository, https://github.com/eddiethedean/sparkforge
Project-URL: Bug Tracker, https://github.com/eddiethedean/sparkforge/issues
Keywords: spark,databricks,pipeline,etl,data-engineering,data-lakehouse,bronze-silver-gold,delta-lake,big-data
Classifier: Development Status :: 3 - Alpha
Classifier: Intended Audience :: Developers
Classifier: Intended Audience :: Science/Research
Classifier: License :: OSI Approved :: MIT License
Classifier: Operating System :: OS Independent
Classifier: Programming Language :: Python :: 3
Classifier: Programming Language :: Python :: 3.8
Classifier: Programming Language :: Python :: 3.9
Classifier: Programming Language :: Python :: 3.10
Classifier: Programming Language :: Python :: 3.11
Classifier: Topic :: Scientific/Engineering :: Information Analysis
Classifier: Topic :: Software Development :: Libraries :: Python Modules
Classifier: Topic :: Database
Classifier: Topic :: Software Development :: Build Tools
Requires-Python: >=3.8
License-File: LICENSE
Requires-Dist: psutil>=5.8.0
Provides-Extra: compat-test
Requires-Dist: pyspark==3.2.4; extra == "compat-test"
Requires-Dist: delta-spark<2.0.0,>=1.2.0; extra == "compat-test"
Provides-Extra: dev
Requires-Dist: black>=23.0.0; extra == "dev"
Requires-Dist: flake8>=6.0.0; extra == "dev"
Requires-Dist: mypy>=1.3.0; extra == "dev"
Requires-Dist: isort>=5.12.0; extra == "dev"
Requires-Dist: pylint>=2.17.0; extra == "dev"
Requires-Dist: bandit>=1.7.0; extra == "dev"
Requires-Dist: pre-commit>=3.0.0; extra == "dev"
Requires-Dist: ruff>=0.0.270; extra == "dev"
Requires-Dist: mypy-extensions>=1.0.0; extra == "dev"
Requires-Dist: types-requests>=2.28.0; extra == "dev"
Requires-Dist: pytest>=7.0.0; extra == "dev"
Requires-Dist: pytest-cov>=4.0.0; extra == "dev"
Requires-Dist: pytest-xdist>=3.0.0; extra == "dev"
Provides-Extra: docs
Requires-Dist: sphinx>=4.0.0; extra == "docs"
Requires-Dist: sphinx-rtd-theme>=1.0.0; extra == "docs"
Requires-Dist: myst-parser>=0.17.0; extra == "docs"
Provides-Extra: mock
Requires-Dist: mock-spark==2.4.0; extra == "mock"
Provides-Extra: pyspark
Requires-Dist: pyspark==3.2.4; extra == "pyspark"
Requires-Dist: delta-spark<2.0.0,>=1.2.0; extra == "pyspark"
Provides-Extra: test
Requires-Dist: mock-spark==2.4.0; extra == "test"
Requires-Dist: pytest>=7.0.0; extra == "test"
Requires-Dist: pytest-cov>=4.0.0; extra == "test"
Requires-Dist: pytest-xdist>=3.0.0; extra == "test"
Requires-Dist: hypothesis>=6.0.0; extra == "test"
Requires-Dist: pyspark==3.2.4; extra == "test"
Requires-Dist: delta-spark<2.0.0,>=1.2.0; extra == "test"
